termgrad/__init__.py
termgrad/colors.py
termgrad-0.1.4.dist-info/METADATA
termgrad-0.1.4.dist-info/WHEEL
termgrad-0.1.4.dist-info/top_level.txt
termgrad-0.1.4.dist-info/RECORD
