Metadata-Version: 2.4
Name: termgrad
Version: 0.1.4
Summary: A python package for nice clean colors for your terminal tools!
Home-page: https://coderhangout.xyz
Author: Wock 2009
License: MIT
Project-URL: Homepage, https://coderhangout.xyz
Keywords: terminal colors gradient text cli
Classifier: Programming Language :: Python :: 3
Classifier: Operating System :: OS Independent
Classifier: License :: OSI Approved :: MIT License
Classifier: Topic :: Software Development :: Libraries
Classifier: Topic :: Utilities
Requires-Python: >=3.6
Dynamic: author
Dynamic: classifier
Dynamic: description
Dynamic: description-content-type
Dynamic: home-page
Dynamic: keywords
Dynamic: license
Dynamic: project-url
Dynamic: requires-python
Dynamic: summary
